[{"content":"","href":"/","title":"Chao Jia"},{"content":"","href":"/tags/dummy/","title":"dummy"},{"content":"Hello there, this is a dummy post, and some dummy update.\n","href":"/posts/2022-03-04-post-01/","title":"Post 1"},{"content":"","href":"/posts/","title":"Posts"},{"content":"","href":"/tags/","title":"Tags"},{"content":"","href":"/authors/","title":"Authors"},{"content":"","href":"/categories/","title":"Categories"},{"content":"","href":"/page/","title":"Pages"},{"content":"","href":"/search/","title":"Search"},{"content":"","href":"/series/","title":"Series"}]